awsiot_credentialhelper/__init__.py
awsiot_credentialhelper/boto3_session.py
awsiot_credentialhelper/py.typed
awsiot_credentialhelper-1.0.2.dist-info/LICENSE
awsiot_credentialhelper-1.0.2.dist-info/METADATA
awsiot_credentialhelper-1.0.2.dist-info/WHEEL
awsiot_credentialhelper-1.0.2.dist-info/RECORD
