Metadata-Version: 2.1
Name: awsiot-credentialhelper
Version: 1.0.2
Summary: AWS IoT Core Credential Provider Session Helper
Home-page: https://github.com/awslabs/aws-iot-core-credential-provider-session-helper
License: Apache-2.0
Author: Gavin Adams
Author-email: gavinaws@amazon.com
Requires-Python: >=3.8.1,<4.0.0
Classifier: Development Status :: 4 - Beta
Classifier: License :: OSI Approved :: Apache Software License
Classifier: Programming Language :: Python :: 3
Classifier: Programming Language :: Python :: 3.9
Classifier: Programming Language :: Python :: 3.10
Classifier: Programming Language :: Python :: 3.11
Classifier: Programming Language :: Python :: 3.12
Requires-Dist: awscrt (>=0.16.9)
Requires-Dist: boto3 (>=1.20.27,<2.0.0)
Requires-Dist: botocore (>=1.23.27,<2.0.0)
Requires-Dist: typing-extensions (>=4.5.0,<5.0.0)
Requires-Dist: urllib3 (>=1.25.4,<1.27)
Project-URL: Changelog, https://github.com/awslabs/aws-iot-core-credential-provider-session-helper/releases
Project-URL: Documentation, https://awslabs.github.io/aws-iot-core-credential-provider-session-helper
Project-URL: Repository, https://github.com/awslabs/aws-iot-core-credential-provider-session-helper
